{
    "ASA_Z3DB0Y": ["dev", "qt", "vip", "artist", "cc", "early-supporter"],
    "maur1005": ["vip", "artist", "early-supporter"],
    "HACKEDurmum": ["vip", "artist", "early-supporter"],
    "Banananana69": ["early-supporter"],
    "AcenoTV": ["cc", "early-supporter"],
    "wham0": ["early-supporter"],
    "forgoted": ["early-supporter"],
    "creepycats": ["early-supporter"],
    "C1RCA_Aircloud": ["early-supporter"],
    "1NoClue1": ["early-supporter"],
    "pro_danny_pro": ["early-supporter"],
    "wcht": ["vip", "early-supporter"],
    "Benitto": ["cc"],
    "SchnellerYT": ["cc"],
    "0oASHASHANGAo0": ["early-supporter"],
    "PhantomGame": ["vip"]
}
